{
  "title": "DICE: The Cube That Changes Everything",
  "description": "[Complete]\nDongtae, a bullied, unpopular high schooler who gets a chance to transform his life when a mysterious transfer student, Taebin, introduces him to magical dice that grant wishes and skills with each roll, but quickly becomes a dark, addictive game where appearance, status, and even fighting power are altered, leading Dongtae down a complex path filled with unforeseen consequences, moral dilemmas, and battles against other \"Dicers\" who seek power, questioning if true change is possible or just a game.",
  "artist": "YUN Hyunseok",
  "author": "YUN Hyunseok",
  "cover": "https://cdn.imgchest.com/files/74f85f11113b.png",
  "chapters": {
    "000": {
      "title": "Prologue",
      "volume": "1",
      "last_updated": "1767102148",
      "groups": {
        "LINE": "/proxy/api/imgchest/chapter/9ryd2o8el4k"
      }
    },
    "001": {
      "title": "Once Thrown A Dice Can't Be Stopped",
      "volume": "1",
      "last_updated": "1767102276",
      "groups": {
        "LINE": "/proxy/api/imgchest/chapter/n87wn25jg7x"
      }
    },
    "002": {
      "title": "And Everything Started To Fall",
      "volume": "1",
      "last_updated": "1767102927",
      "groups": {
        "LINE": "/proxy/api/imgchest/chapter/5xy2omvjz4l"
      }
    },
    "003": {
      "title": "1 Cannot Ever Beat 6",
      "volume": "1",
      "last_updated": "1767103527",
      "groups": {
        "LINE": "/proxy/api/imgchest/chapter/9ryd2o8864k"
      }
    },
    "004": {
      "title": "Congratulations, You've Become A Dicer",
      "volume": "1",
      "last_updated": "1767103641",
      "groups": {
        "LINE": "/proxy/api/imgchest/chapter/qb4zpqvvlyj"
      }
    },
    "005": {
      "title": "God Never Plays Dice",
      "volume": "1",
      "last_updated": "1767106006",
      "groups": {
        "LINE": "/proxy/api/imgchest/chapter/9p4nzmb3w4n"
      }
    },
    "006": {
      "title": "Once The Dice Stops, It Never Rolls Again",
      "volume": "1",
      "last_updated": "1767107050",
      "groups": {
        "LINE": "/proxy/api/imgchest/chapter/md7ob3oqd4p"
      }
    },
    "007": {
      "title": "Once The Dice Stops, It Never Rolls Again (2)",
      "volume": "1",
      "last_updated": "1767123425",
      "groups": {
        "LINE": "/proxy/api/imgchest/chapter/vj4jmjlg548"
      }
    },
    "008": {
      "title": "On The Opposite Side of 1, There Is 6",
      "volume": "1",
      "last_updated": "1767123508",
      "groups": {
        "LINE": "/proxy/api/imgchest/chapter/wl7lwdq2p4x"
      }
    },
    "009": {
      "title": "Move Three Spaces Forward",
      "volume": "1",
      "last_updated": "1767123600",
      "groups": {
        "LINE": "/proxy/api/imgchest/chapter/n87wn2amz7x"
      }
    },
    "010": {
      "title": "Two Dice Roll In Their Own Way",
      "volume": "1",
      "last_updated": "1767123686",
      "groups": {
        "LINE": "/proxy/api/imgchest/chapter/m9yxnl6337q"
      }
    },
    "011": {
      "title": "Move One Space Backwards",
      "volume": "1",
      "last_updated": "1767124343",
      "groups": {
        "LINE": "/proxy/api/imgchest/chapter/m9yxnl6d37q"
      }
    },
    "012": {
      "title": "Once A Dice Has Fallen, It's Useless",
      "volume": "1",
      "last_updated": "1767124437",
      "groups": {
        "LINE": "/proxy/api/imgchest/chapter/vj4jmjln248"
      }
    },
    "013": {
      "title": "On The Opposite Side of 6, There Is 1",
      "volume": "1",
      "last_updated": "1767124531",
      "groups": {
        "LINE": "/proxy/api/imgchest/chapter/ej7merd6nyd"
      }
    },
    "014": {
      "title": "Roll The Bones",
      "volume": "1",
      "last_updated": "1767124620",
      "groups": {
        "LINE": "/proxy/api/imgchest/chapter/o24a6o5m2yl"
      }
    },
    "015": {
      "title": "Alea Iacta Est",
      "volume": "1",
      "last_updated": "1767124728",
      "groups": {
        "LINE": "/proxy/api/imgchest/chapter/md7ob3mvr4p"
      }
    },
    "016": {
      "title": "CHAOS",
      "volume": "1",
      "last_updated": "1767124851",
      "groups": {
        "LINE": "/proxy/api/imgchest/chapter/n87wn2a8g7x"
      }
    },
    "017": {
      "title": "Pandora (1)",
      "volume": "1",
      "last_updated": "1767124947",
      "groups": {
        "LINE": "/proxy/api/imgchest/chapter/o24a6o5d2yl"
      }
    },
    "018": {
      "title": "Pandora (2)",
      "volume": "1",
      "last_updated": "1767125022",
      "groups": {
        "LINE": "/proxy/api/imgchest/chapter/xny868a854b"
      }
    },
    "019": {
      "title": "Pandora (3)",
      "volume": "1",
      "last_updated": "1767125112",
      "groups": {
        "LINE": "/proxy/api/imgchest/chapter/5xy2omkm94l"
      }
    },
    "020": {
      "title": "Pandora (4)",
      "volume": "1",
      "last_updated": "1767125191",
      "groups": {
        "LINE": "/proxy/api/imgchest/chapter/n87wn2abg7x"
      }
    },
    "021": {
      "title": "Pandora (5)",
      "volume": "1",
      "last_updated": "1767125279",
      "groups": {
        "LINE": "/proxy/api/imgchest/chapter/xny868aw54b"
      }
    },
    "022": {
      "title": "Pandora (6)",
      "volume": "1",
      "last_updated": "1767125370",
      "groups": {
        "LINE": "/proxy/api/imgchest/chapter/ne7b6oajjy5"
      }
    },
    "023": {
      "title": "Pandora (7)",
      "volume": "1",
      "last_updated": "1767125436",
      "groups": {
        "LINE": "/proxy/api/imgchest/chapter/ljyqkewbny2"
      }
    },
    "024": {
      "title": "Pandora (8)",
      "volume": "1",
      "last_updated": "1767125526",
      "groups": {
        "LINE": "/proxy/api/imgchest/chapter/pg73o3eag7r"
      }
    },
    "025": {
      "title": "Pandora (9)",
      "volume": "1",
      "last_updated": "1767125604",
      "groups": {
        "LINE": "/proxy/api/imgchest/chapter/9249k56nbyn"
      }
    },
    "026": {
      "title": "A Long Day (1)",
      "volume": "1",
      "last_updated": "1767125691",
      "groups": {
        "LINE": "/proxy/api/imgchest/chapter/ljyqkew3dy2"
      }
    },
    "027": {
      "title": "A Long Day (2)",
      "volume": "1",
      "last_updated": "1767126655",
      "groups": {
        "LINE": "/proxy/api/imgchest/chapter/md7ob32zl4p"
      }
    },
    "028": {
      "title": "A Long Day (3)",
      "volume": "1",
      "last_updated": "1767126706",
      "groups": {
        "LINE": "/proxy/api/imgchest/chapter/ej7merbzayd"
      }
    },
    "029": {
      "title": "A Long Day (4)",
      "volume": "1",
      "last_updated": "1767126797",
      "groups": {
        "LINE": "/proxy/api/imgchest/chapter/o24a6owxeyl"
      }
    },
    "030": {
      "title": "A Long Day (5)",
      "volume": "1",
      "last_updated": "1767126865",
      "groups": {
        "LINE": "/proxy/api/imgchest/chapter/wl7lwdnx34x"
      }
    },
    "031": {
      "title": "A Long Day (6)",
      "volume": "1",
      "last_updated": "1767126949",
      "groups": {
        "LINE": "/proxy/api/imgchest/chapter/9ryd2og5n4k"
      }
    },
    "031.1": {
      "title": "",
      "volume": "1",
      "last_updated": "1767126957",
      "groups": {
        "LINE": "/proxy/api/imgchest/chapter/qe4gqkadb7j"
      }
    },
    "032": {
      "title": "A Long Day (7)",
      "volume": "1",
      "last_updated": "1767127073",
      "groups": {
        "LINE": "/proxy/api/imgchest/chapter/xny868gxd4b"
      }
    },
    "033": {
      "title": "A Long Day (8)",
      "volume": "1",
      "last_updated": "1767127195",
      "groups": {
        "LINE": "/proxy/api/imgchest/chapter/6eyrnzq267p"
      }
    },
    "034": {
      "title": "A Long Day (9)",
      "volume": "1",
      "last_updated": "1767127271",
      "groups": {
        "LINE": "/proxy/api/imgchest/chapter/qb4zpqg3vyj"
      }
    },
    "035": {
      "title": "End of the Day (1)",
      "volume": "1",
      "last_updated": "1767127345",
      "groups": {
        "LINE": "/proxy/api/imgchest/chapter/bp45oew8g75"
      }
    },
    "036": {
      "title": "End of the Day (2)",
      "volume": "1",
      "last_updated": "1767127428",
      "groups": {
        "LINE": "/proxy/api/imgchest/chapter/9249k58jayn"
      }
    },
    "037": {
      "title": "End of the Day (3)",
      "volume": "1",
      "last_updated": "1767127513",
      "groups": {
        "LINE": "/proxy/api/imgchest/chapter/wl7lwdnmo4x"
      }
    },
    "038": {
      "title": "..nd",
      "volume": "1",
      "last_updated": "1767127603",
      "groups": {
        "LINE": "/proxy/api/imgchest/chapter/ej7merb2jyd"
      }
    },
    "039": {
      "title": "Light and Shadow (1)",
      "volume": "1",
      "last_updated": "1767127688",
      "groups": {
        "LINE": "/proxy/api/imgchest/chapter/o24a6owkwyl"
      }
    },
    "040": {
      "title": "Light and Shadow (2)",
      "volume": "1",
      "last_updated": "1767127775",
      "groups": {
        "LINE": "/proxy/api/imgchest/chapter/9p4nzmpxl4n"
      }
    },
    "041": {
      "title": "Light and Shadow (3)",
      "volume": "1",
      "last_updated": "1767127832",
      "groups": {
        "LINE": "/proxy/api/imgchest/chapter/9ryd2ogan4k"
      }
    },
    "042": {
      "title": "Light and Shadow (4)",
      "volume": "1",
      "last_updated": "1767127916",
      "groups": {
        "LINE": "/proxy/api/imgchest/chapter/bp45oewzg75"
      }
    },
    "043": {
      "title": "Light and Shadow (5)",
      "volume": "1",
      "last_updated": "1767128000",
      "groups": {
        "LINE": "/proxy/api/imgchest/chapter/md7ob32e94p"
      }
    },
    "044": {
      "title": "Light and Shadow (6)",
      "volume": "1",
      "last_updated": "1767151765",
      "groups": {
        "LINE": "/proxy/api/imgchest/chapter/n87wnbvdb7x"
      }
    },
    "045": {
      "title": "Domino (1)",
      "volume": "1",
      "last_updated": "1767151863",
      "groups": {
        "LINE": "/proxy/api/imgchest/chapter/9p4nza2jl4n"
      }
    },
    "046": {
      "title": "Domino (2)",
      "volume": "1",
      "last_updated": "1767151951",
      "groups": {
        "LINE": "/proxy/api/imgchest/chapter/ljyqkbqrky2"
      }
    },
    "047": {
      "title": "Domino (3)",
      "volume": "1",
      "last_updated": "1767152018",
      "groups": {
        "LINE": "/proxy/api/imgchest/chapter/n87wnbvxb7x"
      }
    },
    "048": {
      "title": "Domino (4)",
      "volume": "1",
      "last_updated": "1767152114",
      "groups": {
        "LINE": "/proxy/api/imgchest/chapter/agyvnb6rz48"
      }
    },
    "049": {
      "title": "Domino (5)",
      "volume": "1",
      "last_updated": "1767152221",
      "groups": {
        "LINE": "/proxy/api/imgchest/chapter/md7obkl894p"
      }
    },
    "050": {
      "title": "Domino (6)",
      "volume": "1",
      "last_updated": "1767152305",
      "groups": {
        "LINE": "/proxy/api/imgchest/chapter/pg73oqplv7r"
      }
    },
    "051": {
      "title": "Domino (7)",
      "volume": "1",
      "last_updated": "1767152426",
      "groups": {
        "LINE": "/proxy/api/imgchest/chapter/bp45or8mx75"
      }
    },
    "052": {
      "title": "Domino (8)",
      "volume": "1",
      "last_updated": "1767152549",
      "groups": {
        "LINE": "/proxy/api/imgchest/chapter/dl7pnbqa8yo"
      }
    },
    "053": {
      "title": "Mio (1)",
      "volume": "1",
      "last_updated": "1767152749",
      "groups": {
        "LINE": "/proxy/api/imgchest/chapter/pg73oqpdv7r"
      }
    },
    "054": {
      "title": "Domino (9)",
      "volume": "1",
      "last_updated": "1767152856",
      "groups": {
        "LINE": "/proxy/api/imgchest/chapter/agyvnb6nw48"
      }
    },
    "055": {
      "title": "Babel (1)",
      "volume": "1",
      "last_updated": "1767152960",
      "groups": {
        "LINE": "/proxy/api/imgchest/chapter/5xy2ojeon4l"
      }
    },
    "056": {
      "title": "Babel (2)",
      "volume": "1",
      "last_updated": "1767153061",
      "groups": {
        "LINE": "/proxy/api/imgchest/chapter/qe4gq3lqo7j"
      }
    },
    "057": {
      "title": "Babel (3)",
      "volume": "1",
      "last_updated": "1767153152",
      "groups": {
        "LINE": "/proxy/api/imgchest/chapter/ne7b6jpnky5"
      }
    },
    "058": {
      "title": "Babel (4)",
      "volume": "1",
      "last_updated": "1767153254",
      "groups": {
        "LINE": "/proxy/api/imgchest/chapter/vj4jmz3n548"
      }
    },
    "059": {
      "title": "Babel (5)",
      "volume": "1",
      "last_updated": "1767153368",
      "groups": {
        "LINE": "/proxy/api/imgchest/chapter/qe4gq3lpo7j"
      }
    },
    "060": {
      "title": "Babel (6)",
      "volume": "1",
      "last_updated": "1767153539",
      "groups": {
        "LINE": "/proxy/api/imgchest/chapter/dl7pnbq68yo"
      }
    },
    "061": {
      "title": "Babel (7)",
      "volume": "1",
      "last_updated": "1767153772",
      "groups": {
        "LINE": "/proxy/api/imgchest/chapter/pg73oqp8z7r"
      }
    },
    "062": {
      "title": "To be.. [S1 END]",
      "volume": "1",
      "last_updated": "1767153888",
      "groups": {
        "LINE": "/proxy/api/imgchest/chapter/vj4jmz35248"
      }
    },
    "063": {
      "title": "¹⁄₁₆ (1)",
      "volume": "2",
      "last_updated": "1767153977",
      "groups": {
        "LINE": "/proxy/api/imgchest/chapter/9249kea52yn"
      }
    },
    "064": {
      "title": "¹⁄₁₆ (2)",
      "volume": "2",
      "last_updated": "1767154098",
      "groups": {
        "LINE": "/proxy/api/imgchest/chapter/9ryd2dzow4k"
      }
    },
    "065": {
      "title": "¹⁄₁₆ (3)",
      "volume": "2",
      "last_updated": "1767154192",
      "groups": {
        "LINE": "/proxy/api/imgchest/chapter/9p4nza2az4n"
      }
    },
    "066": {
      "title": "¹⁄₁₆ (4)",
      "volume": "2",
      "last_updated": "1767154281",
      "groups": {
        "LINE": "/proxy/api/imgchest/chapter/lqyelrvk34d"
      }
    },
    "067": {
      "title": "¹⁄₁₆ (5)",
      "volume": "2",
      "last_updated": "1767154365",
      "groups": {
        "LINE": "/proxy/api/imgchest/chapter/dl7pnbqp6yo"
      }
    },
    "068": {
      "title": "¹⁄₁₆ (6)",
      "volume": "2",
      "last_updated": "1767154459",
      "groups": {
        "LINE": "/proxy/api/imgchest/chapter/wl7lw8kpq4x"
      }
    },
    "069": {
      "title": "¹⁄₁₆ (7)",
      "volume": "2",
      "last_updated": "1767155154",
      "groups": {
        "LINE": "/proxy/api/imgchest/chapter/m9yxnbv6q7q"
      }
    },
    "070": {
      "title": "¹⁄₁₆ (8)",
      "volume": "2",
      "last_updated": "1767155292",
      "groups": {
        "LINE": "/proxy/api/imgchest/chapter/5xy2ojek94l"
      }
    },
    "071": {
      "title": "Taebin (Mooyoung) I",
      "volume": "2",
      "last_updated": "1767155406",
      "groups": {
        "LINE": "/proxy/api/imgchest/chapter/agyvnb63b48"
      }
    },
    "072": {
      "title": "Taebin (Mooyoung) II",
      "volume": "2",
      "last_updated": "1767155513",
      "groups": {
        "LINE": "/proxy/api/imgchest/chapter/6eyrnb2px7p"
      }
    },
    "073": {
      "title": "Taebin (Mooyoung) III",
      "volume": "2",
      "last_updated": "1767155603",
      "groups": {
        "LINE": "/proxy/api/imgchest/chapter/9p4nza25b4n"
      }
    },
    "074": {
      "title": "Taebin (Mooyoung) IV",
      "volume": "2",
      "last_updated": "1767155767",
      "groups": {
        "LINE": "/proxy/api/imgchest/chapter/lqyelrpjm4d"
      }
    },
    "075": {
      "title": "Taebin (Mooyoung) V",
      "volume": "2",
      "last_updated": "1767155865",
      "groups": {
        "LINE": "/proxy/api/imgchest/chapter/qb4zpbk95yj"
      }
    },
    "076": {
      "title": "Taebin (Mooyoung) VI",
      "volume": "2",
      "last_updated": "1767155960",
      "groups": {
        "LINE": "/proxy/api/imgchest/chapter/a846omgaz4x"
      }
    },
    "077": {
      "title": "Icarus (1)",
      "volume": "2",
      "last_updated": "1767159798",
      "groups": {
        "LINE": "/proxy/api/imgchest/chapter/ej7me52vqyd"
      }
    },
    "078": {
      "title": "Icarus (2)",
      "volume": "2",
      "last_updated": "1767159914",
      "groups": {
        "LINE": "/proxy/api/imgchest/chapter/qe4gq3rpo7j"
      }
    },
    "079": {
      "title": "Icarus (3)",
      "volume": "2",
      "last_updated": "1767160030",
      "groups": {
        "LINE": "/proxy/api/imgchest/chapter/ne7b6jx3ky5"
      }
    },
    "080": {
      "title": "Icarus (4)",
      "volume": "2",
      "last_updated": "1767160136",
      "groups": {
        "LINE": "/proxy/api/imgchest/chapter/6eyrnbd6k7p"
      }
    },
    "081": {
      "title": "Icarus (5)",
      "volume": "2",
      "last_updated": "1767160239",
      "groups": {
        "LINE": "/proxy/api/imgchest/chapter/xny86wlrp4b"
      }
    },
    "082": {
      "title": "The Joker (1)",
      "volume": "2",
      "last_updated": "1767160329",
      "groups": {
        "LINE": "/proxy/api/imgchest/chapter/9p4nzalqw4n"
      }
    },
    "083": {
      "title": "The Joker (2)",
      "volume": "2",
      "last_updated": "1767160433",
      "groups": {
        "LINE": "/proxy/api/imgchest/chapter/wl7lw8ml64x"
      }
    },
    "084": {
      "title": "The Joker (3)",
      "volume": "2",
      "last_updated": "1767160530",
      "groups": {
        "LINE": "/proxy/api/imgchest/chapter/qb4zpbkq3yj"
      }
    },
    "085": {
      "title": "The Joker (4)",
      "volume": "2",
      "last_updated": "1767160611",
      "groups": {
        "LINE": "/proxy/api/imgchest/chapter/9p4nzalmz4n"
      }
    },
    "086": {
      "title": "Eunjoo I",
      "volume": "2",
      "last_updated": "1767160711",
      "groups": {
        "LINE": "/proxy/api/imgchest/chapter/9ryd2dpow4k"
      }
    },
    "087": {
      "title": "Gambit",
      "volume": "2",
      "last_updated": "1767160809",
      "groups": {
        "LINE": "/proxy/api/imgchest/chapter/bp45ordr275"
      }
    },
    "088": {
      "title": "First Period (1)",
      "volume": "2",
      "last_updated": "1767160900",
      "groups": {
        "LINE": "/proxy/api/imgchest/chapter/ne7b6jxjny5"
      }
    },
    "089": {
      "title": "First Period (2)",
      "volume": "2",
      "last_updated": "1767161008",
      "groups": {
        "LINE": "/proxy/api/imgchest/chapter/na7kkgwgq78"
      }
    },
    "090": {
      "title": "First Period (3)",
      "volume": "2",
      "last_updated": "1767161082",
      "groups": {
        "LINE": "/proxy/api/imgchest/chapter/vj4jmzwz248"
      }
    },
    "091": {
      "title": "First Period (4)",
      "volume": "2",
      "last_updated": "1767161175",
      "groups": {
        "LINE": "/proxy/api/imgchest/chapter/ej7me525byd"
      }
    },
    "092": {
      "title": "First Period (5)",
      "volume": "2",
      "last_updated": "1767161268",
      "groups": {
        "LINE": "/proxy/api/imgchest/chapter/xny86wlno4b"
      }
    },
    "093": {
      "title": "Samsusaeng",
      "volume": "2",
      "last_updated": "1767161361",
      "groups": {
        "LINE": "/proxy/api/imgchest/chapter/md7obkjpd4p"
      }
    },
    "094": {
      "title": "First Period (6)",
      "volume": "2",
      "last_updated": "1767161461",
      "groups": {
        "LINE": "/proxy/api/imgchest/chapter/n87wnbr5z7x"
      }
    },
    "095": {
      "title": "First Period (7)",
      "volume": "2",
      "last_updated": "1767161558",
      "groups": {
        "LINE": "/proxy/api/imgchest/chapter/lqyelrp534d"
      }
    },
    "096": {
      "title": "First Period > Break",
      "volume": "2",
      "last_updated": "1767161651",
      "groups": {
        "LINE": "/proxy/api/imgchest/chapter/m9yxnbga37q"
      }
    },
    "097": {
      "title": "Break (2)",
      "volume": "2",
      "last_updated": "1767161740",
      "groups": {
        "LINE": "/proxy/api/imgchest/chapter/ljyqkbd3oy2"
      }
    },
    "098": {
      "title": "End of Break",
      "volume": "2",
      "last_updated": "1767161875",
      "groups": {
        "LINE": "/proxy/api/imgchest/chapter/xny86wlj54b"
      }
    },
    "099": {
      "title": "Second Period (1)",
      "volume": "2",
      "last_updated": "1767161946",
      "groups": {
        "LINE": "/proxy/api/imgchest/chapter/vj4jmzwbx48"
      }
    },
    "100": {
      "title": "Second Period (2)",
      "volume": "2",
      "last_updated": "1767162047",
      "groups": {
        "LINE": "/proxy/api/imgchest/chapter/n87wnbr3g7x"
      }
    },
    "100.5": {
      "title": "Bonus Stage 1",
      "volume": "2",
      "last_updated": "1767162058",
      "groups": {
        "LINE": "/proxy/api/imgchest/chapter/o24a6lkr2yl"
      }
    },
    "101": {
      "title": "Second Period (3)",
      "volume": "2",
      "last_updated": "1767162149",
      "groups": {
        "LINE": "/proxy/api/imgchest/chapter/a846omgjo4x"
      }
    },
    "102": {
      "title": "Second Period (4)",
      "volume": "2",
      "last_updated": "1767162243",
      "groups": {
        "LINE": "/proxy/api/imgchest/chapter/9249kejrmyn"
      }
    },
    "103": {
      "title": "The Versus Game",
      "volume": "2",
      "last_updated": "1767162359",
      "groups": {
        "LINE": "/proxy/api/imgchest/chapter/na7kkgw6b78"
      }
    },
    "104": {
      "title": "Second Period (5)",
      "volume": "2",
      "last_updated": "1767162457",
      "groups": {
        "LINE": "/proxy/api/imgchest/chapter/pg73oqjej7r"
      }
    },
    "105": {
      "title": "Zugzwang",
      "volume": "2",
      "last_updated": "1767162566",
      "groups": {
        "LINE": "/proxy/api/imgchest/chapter/m9yxnbg6q7q"
      }
    },
    "106": {
      "title": "Third Period (1)",
      "volume": "2",
      "last_updated": "1767162693",
      "groups": {
        "LINE": "/proxy/api/imgchest/chapter/wl7lw8mqq4x"
      }
    },
    "107": {
      "title": "Third Period (2)",
      "volume": "2",
      "last_updated": "1767162797",
      "groups": {
        "LINE": "/proxy/api/imgchest/chapter/lqyelrp8q4d"
      }
    },
    "108": {
      "title": "Third Period (3)",
      "volume": "2",
      "last_updated": "1767162920",
      "groups": {
        "LINE": "/proxy/api/imgchest/chapter/9249kej8myn"
      }
    },
    "109": {
      "title": "Taebin (Mooyoung) VII",
      "volume": "2",
      "last_updated": "1767163055",
      "groups": {
        "LINE": "/proxy/api/imgchest/chapter/wl7lw8mnq4x"
      }
    },
    "110": {
      "title": "The Castling",
      "volume": "2",
      "last_updated": "1767163174",
      "groups": {
        "LINE": "/proxy/api/imgchest/chapter/6eyrnbdpx7p"
      }
    },
    "111": {
      "title": "Third Period (4)",
      "volume": "2",
      "last_updated": "1767163254",
      "groups": {
        "LINE": "/proxy/api/imgchest/chapter/a846omgvz4x"
      }
    },
    "112": {
      "title": "Third Period (5)",
      "volume": "2",
      "last_updated": "1767163325",
      "groups": {
        "LINE": "/proxy/api/imgchest/chapter/ne7b6jx8my5"
      }
    },
    "113": {
      "title": "Check",
      "volume": "2",
      "last_updated": "1767163414",
      "groups": {
        "LINE": "/proxy/api/imgchest/chapter/5xy2oj3zz4l"
      }
    },
    "114": {
      "title": "Zwischenzug (Queen's Gambit)",
      "volume": "2",
      "last_updated": "1767163509",
      "groups": {
        "LINE": "/proxy/api/imgchest/chapter/vj4jmzvo348"
      }
    },
    "115": {
      "title": "Third Period (6)..?",
      "volume": "2",
      "last_updated": "1767163625",
      "groups": {
        "LINE": "/proxy/api/imgchest/chapter/n87wnbgzx7x"
      }
    },
    "116": {
      "title": "Stalemate",
      "volume": "2",
      "last_updated": "1767163736",
      "groups": {
        "LINE": "/proxy/api/imgchest/chapter/a846omkrz4x"
      }
    },
    "117": {
      "title": "Parallel lines",
      "volume": "2",
      "last_updated": "1767163831",
      "groups": {
        "LINE": "/proxy/api/imgchest/chapter/md7obkxz24p"
      }
    },
    "118": {
      "title": "A Sunday Beyond Dice (1)",
      "volume": "2",
      "last_updated": "1767163928",
      "groups": {
        "LINE": "/proxy/api/imgchest/chapter/9ryd2da5a4k"
      }
    }
  }
}
